binaryceo/__init__.py
binaryceo/fitness.py
binaryceo/initialization.py
binaryceo/optimizer.py
binaryceo/partitioning.py
binaryceo/position_update.py
binaryceo/selection.py
binaryceo/solution.py
binaryceo/termination.py
binaryceo-0.1.0.dist-info/licenses/LICENSE
binaryceo-0.1.0.dist-info/METADATA
binaryceo-0.1.0.dist-info/WHEEL
binaryceo-0.1.0.dist-info/top_level.txt
binaryceo-0.1.0.dist-info/RECORD
