Metadata-Version: 2.4
Name: binaryceo
Version: 0.1.0
Summary: Binary Cosmic Evolution Algorithm for optimization problems
Author-email: Sanat S <sanat.shirwaicar@gmail.com>
License: MIT
Project-URL: Homepage, https://github.com/Optimization-MetaheuristicsCEO/BinaryCEO
Project-URL: Repository, https://github.com/Optimization-MetaheuristicsCEO/BinaryCEO
Project-URL: Issues, https://github.com/Optimization-MetaheuristicsCEO/BinaryCEO/issues
Keywords: optimization,metaheuristics,evolutionary-algorithm,ceo,binary-optimization
Classifier: Development Status :: 3 - Alpha
Classifier: Intended Audience :: Science/Research
Classifier: License :: OSI Approved :: MIT License
Classifier: Programming Language :: Python :: 3
Classifier: Programming Language :: Python :: 3.8
Classifier: Programming Language :: Python :: 3.9
Classifier: Programming Language :: Python :: 3.10
Classifier: Programming Language :: Python :: 3.11
Classifier: Programming Language :: Python :: 3.12
Classifier: Topic :: Scientific/Engineering :: Artificial Intelligence
Requires-Python: >=3.8
License-File: LICENSE
Requires-Dist: numpy>=1.20.0
Requires-Dist: scikit-learn>=1.0
Provides-Extra: dev
Requires-Dist: pytest>=7.0.0; extra == "dev"
Requires-Dist: pytest-cov>=4.0.0; extra == "dev"
Requires-Dist: black>=23.0.0; extra == "dev"
Requires-Dist: flake8>=6.0.0; extra == "dev"
Requires-Dist: mypy>=1.0.0; extra == "dev"
Requires-Dist: isort>=5.12.0; extra == "dev"
Provides-Extra: docs
Requires-Dist: sphinx>=5.0.0; extra == "docs"
Requires-Dist: sphinx-rtd-theme>=1.0.0; extra == "docs"
Dynamic: license-file
